spc_toolbox/ControlChart.py
spc_toolbox/IChart.py
spc_toolbox/MRChart.py
spc_toolbox/PChart.py
spc_toolbox/RChart.py
spc_toolbox/SChart.py
spc_toolbox/UChart.py
spc_toolbox/XBarChart.py
spc_toolbox/__init__.py
spc_toolbox/utils.py
spc_toolbox-0.1.2.dist-info/LICENSE
spc_toolbox-0.1.2.dist-info/METADATA
spc_toolbox-0.1.2.dist-info/WHEEL
spc_toolbox-0.1.2.dist-info/RECORD
