Metadata-Version: 2.1
Name: spc-toolbox
Version: 0.1.2
Summary: A toolbox for Statistical Process Control
Author: Philip Solarz
Author-email: philip.solarz@teliacompany.com
Requires-Python: >=3.10,<4.0
Classifier: Programming Language :: Python :: 3
Classifier: Programming Language :: Python :: 3.10
Classifier: Programming Language :: Python :: 3.11
Requires-Dist: matplotlib (>=3.8.3,<4.0.0)
Requires-Dist: numpy (>=1.26.4,<2.0.0)
Requires-Dist: pandas (>=2.2.1,<3.0.0)
